odoo/addons/account_bank_statement_clearing_account/README.rst
odoo/addons/account_bank_statement_clearing_account/__init__.py
odoo/addons/account_bank_statement_clearing_account/__manifest__.py
odoo/addons/account_bank_statement_clearing_account/i18n/account_bank_statement_clearing_account.pot
odoo/addons/account_bank_statement_clearing_account/models/__init__.py
odoo/addons/account_bank_statement_clearing_account/models/account_bank_statement.py
odoo/addons/account_bank_statement_clearing_account/readme/CONFIGURE.rst
odoo/addons/account_bank_statement_clearing_account/readme/CONTRIBUTORS.rst
odoo/addons/account_bank_statement_clearing_account/readme/DESCRIPTION.rst
odoo/addons/account_bank_statement_clearing_account/readme/USAGE.rst
odoo/addons/account_bank_statement_clearing_account/static/description/icon.png
odoo/addons/account_bank_statement_clearing_account/static/description/index.html
odoo/addons/account_bank_statement_clearing_account/tests/__init__.py
odoo/addons/account_bank_statement_clearing_account/tests/test_clearing_account.py
odoo13_addon_account_bank_statement_clearing_account-13.0.1.0.1.dev4.dist-info/METADATA
odoo13_addon_account_bank_statement_clearing_account-13.0.1.0.1.dev4.dist-info/WHEEL
odoo13_addon_account_bank_statement_clearing_account-13.0.1.0.1.dev4.dist-info/top_level.txt
odoo13_addon_account_bank_statement_clearing_account-13.0.1.0.1.dev4.dist-info/RECORD
